fontcrusher/__init__.py
fontcrusher/css_crush.py
fontcrusher/find_used_glyphs.py
fontcrusher/fontcrusher.py
fontcrusher/get_glyph_name.py
fontcrusher-0.1.0.dist-info/DESCRIPTION.rst
fontcrusher-0.1.0.dist-info/METADATA
fontcrusher-0.1.0.dist-info/RECORD
fontcrusher-0.1.0.dist-info/WHEEL
fontcrusher-0.1.0.dist-info/metadata.json
fontcrusher-0.1.0.dist-info/top_level.txt
