Metadata-Version: 1.1
Name: fontcrusher
Version: 0.1.0
Summary: A python module for reducing the size of fonts by removing unnessasary glyphs
Home-page: http://github.com/AceLewis/fontcrusher
Author: AceLewis
Author-email: UNKNOWN
License: AGPLv3
Download-URL: https://github.com/AceLewis/fontcrusher/archive/master.zip
Keywords: fontcrusher,font,subset,minify,compress,font subset
Platform: UNKNOWN
Classifier: Natural Language :: English
Classifier: Programming Language :: Python
Classifier: Programming Language :: Python :: 2
Classifier: Programming Language :: Python :: 3
Classifier: Natural Language :: English
Classifier: Operating System :: OS Independent
Classifier: License :: OSI Approved :: GNU Affero General Public License v3
Classifier: Topic :: Text Processing :: Fonts
